{
  "project_info": {
    "project_number": "954124236353",
    "project_id": "cicdpro69",
    "storage_bucket": "cicdpro69.firebasestorage.app"
  },
  "client": [
    {
      "client_info": {
        "mobilesdk_app_id": "1:954124236353:android:d8ab03c211623bc28438c0",
        "android_client_info": {
          "package_name": "com.awesomeproject"
        }
      },
      "oauth_client": [],
      "api_key": [
        {
          "current_key": "AIzaSyBKjOzSVIR365VGr4YR9jNcMzP5cd1-xGU"
        }
      ],
      "services": {
        "appinvite_service": {
          "other_platform_oauth_client": []
        }
      }
    }
  ],
  "configuration_version": "1"
}